datacenter_client/__init__.py
datacenter_client/base.py
datacenter_client/client.py
datacenter_client/exceptions.py
datacenter_client/run_tests.py
datacenter_client/tests/__init__.py
datacenter_client/tests/base.py
alphaaidig_datacenter_client-0.1.23.dist-info/METADATA
alphaaidig_datacenter_client-0.1.23.dist-info/WHEEL
alphaaidig_datacenter_client-0.1.23.dist-info/top_level.txt
alphaaidig_datacenter_client-0.1.23.dist-info/RECORD
