Metadata-Version: 2.4
Name: alphaaidig-datacenter-client
Version: 0.1.23
Author-email: Hang GuangLiang <hanguangliang@alphaaidig.com>
Requires-Dist: httpx
Requires-Dist: alphaaidig-datacenter-common==0.1.23
